{
  "projects": [
    {
      "title": "Admin Prime Dashboard",
      "desc": "A custom tablet workstation with a live schedule, focus timer, and Spotify playlist embeded.",
      "link": "https://alcantaras.github.io/ash-admin-dash/",
      "tags": ["React", "Tailwind", "API"]
    },
    {
      "title": "Anxiety Tracker",
      "desc": "Track those anxiety attacks!",
      "link": "https://google.com",
      "tags": ["JSON", "Fetch", "Portfolio"]
    }
  ], 
  "blogPosts": [
    {
      "date": "April 22, 2026",
      "title": "Building Admin Prime: My First React Project",
      "content": "Today I tackled the challenge of building a custom dashboard for my work desk...",
      "category": "Coding"
    },
    {
      "date": "April 23, 2026",
      "title": "Debugging the Great Comma Crisis",
      "content": "I learned the hard way that JSON is incredibly picky. One missing comma between projects and blog posts stopped the whole system...",
      "category": "Learning"
    }
  ]
}
